[{"id":1,"recipient":"345678","text":"hello"},{"id":1,"recipient":"1","text":"1"},{"id":1,"recipient":"formeo","text":"kk"},{"id":1,"recipient":"67","text":"1"},{"id":1,"recipient":"d","text":"h"},{"id":1,"recipient":"00","text":"idcjic"},{"id":1,"recipient":"+27123456789","text":"Hello"},{"id":1,"recipient":"+27123456789","text":"hello"},{"id":1,"recipient":"+27123456789","text":"hello"},{"id":2,"recipient":"+27123456789","text":"bye"},{"id":5497041427,"recipient":"+27123456789","text":"bye","hash":"54:1:BYEBYE"},{"id":4987862933,"recipient":"+27123456789","text":"hi","hash":"49:1:HIHI"},{"id":5452822440,"recipient":"+27123456789","text":"bye","hash":"54:2:BYEBYE"},{"id":6997680520,"recipient":"+27123456789","text":"hi","hash":"69:1:HIHI"},{"id":2044932233,"recipient":"+27123456789","text":"hi","hash":"20:1:HIHI"},{"id":1236706245,"recipient":"+27123456789","text":"exist","hash":"12:1:EXISTEXIST"},{"id":9852015230,"recipient":"+27123456789","text":"hi","hash":"98:1:HIHI"},{"id":1238785650,"recipient":"+27123456789","text":"exist","hash":"12:1:EXISTEXIST"},{"id":2348607319,"recipient":"+27123456789","text":"Hello!","hash":"23:1:HELLO!HELLO!"},{"id":0}]